Files_Cloud_Backuper-0.3.1.dist-info/top_level.txt
Files_Cloud_Backuper-0.3.1.dist-info/metadata.json
Files_Cloud_Backuper-0.3.1.dist-info/WHEEL
Files_Cloud_Backuper-0.3.1.dist-info/entry_points.txt
Files_Cloud_Backuper-0.3.1.dist-info/METADATA
Files_Cloud_Backuper-0.3.1.dist-info/RECORD
Files_Cloud_Backuper-0.3.1.dist-info/DESCRIPTION.rst
fcb/untransform_file.py
fcb/files_cloud_backuper.py
fcb/log_configuration.py
fcb/fcb_launcher.py
fcb/__init__.py
fcb/upload_checker.py
fcb/db_cleanup.py
fcb/checker/mega.py
fcb/checker/mail.py
fcb/checker/__init__.py
fcb/checker/settings.py
fcb/checker/cleanup/helper.py
fcb/checker/cleanup/__init__.py
fcb/framework/__init__.py
fcb/framework/workflow/PipelineTask.py
fcb/framework/workflow/ParallelTaskGroup.py
fcb/framework/workflow/__init__.py
fcb/framework/workflow/Pipeline.py
fcb/framework/workflow/SenderTask.py
fcb/database/schema.py
fcb/database/helpers.py
fcb/database/__init__.py
fcb/database/settings.py
fcb/utils/debugging.py
fcb/utils/log_helper.py
fcb/utils/__init__.py
fcb/utils/trickle.py
fcb/utils/Settings.py
fcb/utils/digest.py
fcb/processing/__init__.py
fcb/processing/models/Quota.py
fcb/processing/models/__init__.py
fcb/processing/models/FileInfo.py
fcb/processing/transformations/Cipher.py
fcb/processing/transformations/ToImage.py
fcb/processing/transformations/__init__.py
fcb/processing/filesystem/FileReader.py
fcb/processing/filesystem/__init__.py
fcb/processing/filesystem/Settings.py
fcb/processing/filesystem/Compressor.py
fcb/processing/filesystem/Cleaner.py
fcb/processing/filters/AlreadyProcessedFilter.py
fcb/processing/filters/FileSizeFilter.py
fcb/processing/filters/__init__.py
fcb/processing/filters/QuotaFilter.py
fcb/sending/Errors.py
fcb/sending/__init__.py
fcb/sending/SentLog.py
fcb/sending/mail/mail.py
fcb/sending/mail/__init__.py
fcb/sending/mail/MailSender.py
fcb/sending/mega/helpers.py
fcb/sending/mega/MegaSender.py
fcb/sending/mega/__init__.py
fcb/sending/directory/__init__.py
fcb/sending/directory/ToDirectorySender.py
fcb/sending/debug/SlowSender.py
fcb/sending/debug/FakeSender.py
fcb/sending/debug/__init__.py
