Metadata-Version: 2.0
Name: Files-Cloud-Backuper
Version: 0.3.1
Summary: Files Cloud Backuper (FCB) automates the process of uploading files to cloud storage services
Home-page: https://github.com/MatiasSM/fcb
Author: MatiasSM
Author-email: UNKNOWN
License: LGPL v3.0
Keywords: backup storage internet
Platform: UNKNOWN
Classifier: Development Status :: 3 - Alpha
Classifier: Intended Audience :: End Users/Desktop
Classifier: Topic :: System :: Archiving :: Backup
Classifier: License :: OSI Approved :: GNU Lesser General Public License v3 (LGPLv3)
Classifier: Programming Language :: Python :: 2.7
Requires-Dist: sqlalchemy
Requires-Dist: subprocess32
Requires-Dist: python-dateutil
Requires-Dist: numpy
Requires-Dist: pycrypto
Requires-Dist: pillow
